contrastive_learner/__init__.py
contrastive_learner/contrastive_learner.py
contrastive_learner-0.1.1.dist-info/LICENSE
contrastive_learner-0.1.1.dist-info/METADATA
contrastive_learner-0.1.1.dist-info/WHEEL
contrastive_learner-0.1.1.dist-info/top_level.txt
contrastive_learner-0.1.1.dist-info/RECORD
