Metadata-Version: 2.1
Name: contrastive-learner
Version: 0.1.1
Summary: Self-supervised contrastive learning made simple
Home-page: https://github.com/lucidrains/contrastive-learner
Author: Phil Wang
Author-email: lucidrains@gmail.com
License: MIT
Keywords: self-supervised learning,artificial intelligence
Platform: UNKNOWN
Classifier: Development Status :: 4 - Beta
Classifier: Intended Audience :: Developers
Classifier: Topic :: Scientific/Engineering :: Artificial Intelligence
Classifier: License :: OSI Approved :: MIT License
Classifier: Programming Language :: Python :: 3.6
Requires-Dist: torch
Requires-Dist: kornia
